Ecust.py
JWC_functions.py
JWC_login.py
URP_login.py
jwc_functions.py
jwc_login.py
urp_functions.py
urp_login.py
Ecust-0.0.3.data/scripts/Ecust.py
Ecust-0.0.3.data/scripts/Ecust_cli.py
Ecust-0.0.3.dist-info/DESCRIPTION.rst
Ecust-0.0.3.dist-info/METADATA
Ecust-0.0.3.dist-info/RECORD
Ecust-0.0.3.dist-info/WHEEL
Ecust-0.0.3.dist-info/entry_points.txt
Ecust-0.0.3.dist-info/metadata.json
Ecust-0.0.3.dist-info/top_level.txt
