Metadata-Version: 2.0
Name: Ecust
Version: 0.0.3
Summary: Ecust Login Module and Some Functions
Home-page: http://github.com/maoxs2/Ecust
Author: Command
Author-email: maoxs2@163.com
License: MIT
Keywords: Ecust
Platform: UNKNOWN
Classifier: Development Status :: 3 - Alpha
Classifier: Intended Audience :: Developers
Classifier: Topic :: Software Development :: Build Tools
Classifier: License :: OSI Approved :: MIT License
Classifier: Programming Language :: Python :: 2
Classifier: Programming Language :: Python :: 2.7
Classifier: Programming Language :: Python :: 3
Classifier: Programming Language :: Python :: 3.5
Requires-Dist: lxml
Requires-Dist: requests
